app_util/__init__.py
app_util/config.py
app_util/connections.py
app_util/util.py
app_utilities-0.1.9.dist-info/METADATA
app_utilities-0.1.9.dist-info/RECORD
app_utilities-0.1.9.dist-info/WHEEL
app_utilities-0.1.9.dist-info/top_level.txt
