Metadata-Version: 2.1
Name: app-utilities
Version: 0.1.9
Summary: A utility to fast-track application configurations
Home-page: https://github.com/Himself12794/app-utilities
Author: Philip Whiting
Author-email: phwhitin@cisco.com
License: UNKNOWN
Download-URL: https://github.com/Himself12794/app-utilities/archive/v0.1.9.tar.gz
Keywords: configuration,utility
Platform: UNKNOWN
Requires-Dist: pymongo (>=3.0.0)
Requires-Dist: requests (>=2.0.0)
